sourcemap/__init__.py
sourcemap/decoder.py
sourcemap/exceptions.py
sourcemap/objects.py
sourcemap-0.2.1.dist-info/DESCRIPTION.rst
sourcemap-0.2.1.dist-info/METADATA
sourcemap-0.2.1.dist-info/RECORD
sourcemap-0.2.1.dist-info/WHEEL
sourcemap-0.2.1.dist-info/metadata.json
sourcemap-0.2.1.dist-info/top_level.txt
